pytest_runtime_types/VERSION
pytest_runtime_types/__init__.py
pytest_runtime_types/collector.py
pytest_runtime_types/type_checker.py
pytest_runtime_types-0.1.0.dist-info/LICENSE
pytest_runtime_types-0.1.0.dist-info/METADATA
pytest_runtime_types-0.1.0.dist-info/WHEEL
pytest_runtime_types-0.1.0.dist-info/top_level.txt
pytest_runtime_types-0.1.0.dist-info/RECORD
